matrix_webhook/__main__.py
matrix_webhook/app.py
matrix_webhook/conf.py
matrix_webhook/formatters.py
matrix_webhook/handler.py
matrix_webhook/utils.py
matrix_webhook-3.9.1.dist-info/LICENSE
matrix_webhook-3.9.1.dist-info/METADATA
matrix_webhook-3.9.1.dist-info/WHEEL
matrix_webhook-3.9.1.dist-info/entry_points.txt
matrix_webhook-3.9.1.dist-info/RECORD
