Metadata-Version: 2.1
Name: matrix-webhook
Version: 3.9.1
Summary: Post a message to a matrix room with a simple HTTP POST
Home-page: https://github.com/nim65s/matrix-webhook
License: BSD-2-Clause
Author: Guilhem Saurel
Author-email: guilhem.saurel@laas.fr
Requires-Python: >=3.8,<4.0
Classifier: License :: OSI Approved :: BSD License
Classifier: Programming Language :: Python :: 3
Classifier: Programming Language :: Python :: 3.8
Classifier: Programming Language :: Python :: 3.9
Classifier: Programming Language :: Python :: 3.10
Classifier: Programming Language :: Python :: 3.11
Classifier: Programming Language :: Python :: 3.12
Requires-Dist: Markdown (>=3.5.2,<4.0.0)
Requires-Dist: matrix-nio (>=0.24,<0.25)
Project-URL: Repository, https://github.com/nim65s/matrix-webhook.git
Project-URL: changelog, https://github.com/nim65s/matrix-webhook/blob/master/CHANGELOG.md
